encrypt_tools_library/__init__.py
encrypt_tools_library/core.py
encrypt_tools_library-0.1.20.dist-info/LICENSE
encrypt_tools_library-0.1.20.dist-info/METADATA
encrypt_tools_library-0.1.20.dist-info/WHEEL
encrypt_tools_library-0.1.20.dist-info/top_level.txt
encrypt_tools_library-0.1.20.dist-info/RECORD
