Metadata-Version: 2.1
Name: encrypt-tools-library
Version: 0.1.20
Summary: encrypt tools
Author-email: xD <1257974173@qq.com>
License: MIT License
Project-URL: Homepage, https://github.com/edsionxuanxuan/encrypt_tools_library
Keywords: example,pypi,package
Classifier: Programming Language :: Python :: 3
Classifier: License :: OSI Approved :: MIT License
Requires-Python: >=3.11
License-File: LICENSE
Requires-Dist: pycryptodome>=3.23.0
